ftpcli/__init__.py
ftpcli/ftp.py
ftpcli-1.0.2.dist-info/METADATA
ftpcli-1.0.2.dist-info/WHEEL
ftpcli-1.0.2.dist-info/top_level.txt
ftpcli-1.0.2.dist-info/RECORD
